{"ticker": "AMT", "quarters": [{"date": "2026-04-28", "time": "08:00", "eps_actual": null, "eps_estimate": 1.57, "eps_surprise_pct": null, "revenue": null, "revenue_yoy": null}, {"date": "2026-02-24", "time": "07:00", "eps_actual": 1.75, "eps_estimate": 1.47, "eps_surprise_pct": 19.05, "revenue": 2737500000, "revenue_yoy": 7.5}, {"date": "2025-10-28", "time": "07:00", "eps_actual": 1.82, "eps_estimate": 1.65, "eps_surprise_pct": 10.06, "revenue": 2717400000, "revenue_yoy": null}, {"date": "2025-07-29", "time": "07:00", "eps_actual": 0.78, "eps_estimate": 1.66, "eps_surprise_pct": -53.01, "revenue": 2626900000, "revenue_yoy": null}, {"date": "2025-04-29", "time": "07:00", "eps_actual": 1.04, "eps_estimate": 1.57, "eps_surprise_pct": -33.66, "revenue": 2562800000, "revenue_yoy": null}, {"date": "2025-02-24", "time": "19:00", "eps_actual": 2.62, "eps_estimate": 1.98, "eps_surprise_pct": 32.02, "revenue": 2547600000, "revenue_yoy": null}, {"date": "2024-10-29", "time": "07:00", "eps_actual": -1.7, "eps_estimate": 1.58, "eps_surprise_pct": -207.7, "revenue": null, "revenue_yoy": null}, {"date": "2024-07-30", "time": "07:00", "eps_actual": 1.92, "eps_estimate": 1.58, "eps_surprise_pct": 21.86, "revenue": null, "revenue_yoy": null}, {"date": "2024-04-30", "time": "07:00", "eps_actual": 1.96, "eps_estimate": 1.76, "eps_surprise_pct": 11.15, "revenue": null, "revenue_yoy": null}, {"date": "2024-02-27", "time": "07:00", "eps_actual": 0.25, "eps_estimate": 0.94, "eps_surprise_pct": -73.86, "revenue": null, "revenue_yoy": null}, {"date": "2023-10-26", "time": "07:00", "eps_actual": 1.88, "eps_estimate": 1.13, "eps_surprise_pct": 65.94, "revenue": null, "revenue_yoy": null}, {"date": "2023-07-27", "time": "07:00", "eps_actual": 1.02, "eps_estimate": 1.08, "eps_surprise_pct": -5.65, "revenue": null, "revenue_yoy": null}]}