{"ticker": "CCL", "quarters": [{"date": "2026-03-19", "time": "08:00", "eps_actual": null, "eps_estimate": 0.18, "eps_surprise_pct": null, "revenue": null, "revenue_yoy": null}, {"date": "2025-12-19", "time": "09:00", "eps_actual": 0.34, "eps_estimate": 0.25, "eps_surprise_pct": 38.64, "revenue": 6330000000, "revenue_yoy": 6.6}, {"date": "2025-09-29", "time": "09:00", "eps_actual": 1.43, "eps_estimate": 1.32, "eps_surprise_pct": 8.54, "revenue": 8153000000, "revenue_yoy": null}, {"date": "2025-06-24", "time": "09:00", "eps_actual": 0.35, "eps_estimate": 0.24, "eps_surprise_pct": 45.31, "revenue": 6328000000, "revenue_yoy": null}, {"date": "2025-03-21", "time": "09:00", "eps_actual": -0.06, "eps_estimate": 0.02, "eps_surprise_pct": -434.08, "revenue": 5810000000, "revenue_yoy": null}, {"date": "2024-12-20", "time": "09:00", "eps_actual": 0.14, "eps_estimate": 0.07, "eps_surprise_pct": 93.99, "revenue": 5938000000, "revenue_yoy": null}, {"date": "2024-09-30", "time": "09:00", "eps_actual": 1.27, "eps_estimate": 1.15, "eps_surprise_pct": 10.0, "revenue": null, "revenue_yoy": null}, {"date": "2024-06-25", "time": "09:00", "eps_actual": 0.11, "eps_estimate": -0.02, "eps_surprise_pct": 692.67, "revenue": null, "revenue_yoy": null}, {"date": "2024-03-27", "time": "09:00", "eps_actual": -0.14, "eps_estimate": -0.18, "eps_surprise_pct": 22.13, "revenue": null, "revenue_yoy": null}, {"date": "2023-12-21", "time": "09:00", "eps_actual": -0.07, "eps_estimate": -0.13, "eps_surprise_pct": 44.27, "revenue": null, "revenue_yoy": null}, {"date": "2023-09-29", "time": "09:00", "eps_actual": 0.86, "eps_estimate": 0.74, "eps_surprise_pct": 16.06, "revenue": null, "revenue_yoy": null}, {"date": "2023-06-26", "time": "09:00", "eps_actual": -0.31, "eps_estimate": -0.34, "eps_surprise_pct": 8.14, "revenue": null, "revenue_yoy": null}]}