{"ticker": "CELH", "quarters": [{"date": "2026-05-11", "time": "08:00", "eps_actual": null, "eps_estimate": 0.3, "eps_surprise_pct": null, "revenue": null, "revenue_yoy": null}, {"date": "2026-02-26", "time": "06:00", "eps_actual": 0.26, "eps_estimate": 0.19, "eps_surprise_pct": 36.91, "revenue": 721628000, "revenue_yoy": 117.2}, {"date": "2025-11-06", "time": "06:00", "eps_actual": 0.42, "eps_estimate": 0.28, "eps_surprise_pct": 52.05, "revenue": 725106000, "revenue_yoy": null}, {"date": "2025-08-07", "time": "06:00", "eps_actual": 0.47, "eps_estimate": 0.24, "eps_surprise_pct": 93.07, "revenue": 739259000, "revenue_yoy": null}, {"date": "2025-05-06", "time": "06:00", "eps_actual": 0.15, "eps_estimate": 0.19, "eps_surprise_pct": -21.37, "revenue": 329276000, "revenue_yoy": null}, {"date": "2025-02-20", "time": "16:00", "eps_actual": 0.14, "eps_estimate": 0.1, "eps_surprise_pct": 44.21, "revenue": 332197000, "revenue_yoy": null}, {"date": "2024-11-06", "time": "06:00", "eps_actual": null, "eps_estimate": 0.01, "eps_surprise_pct": -143.94, "revenue": null, "revenue_yoy": null}, {"date": "2024-08-06", "time": "06:00", "eps_actual": 0.28, "eps_estimate": 0.25, "eps_surprise_pct": 11.22, "revenue": null, "revenue_yoy": null}, {"date": "2024-05-07", "time": "06:00", "eps_actual": 0.27, "eps_estimate": 0.19, "eps_surprise_pct": 43.97, "revenue": null, "revenue_yoy": null}, {"date": "2024-02-29", "time": "06:00", "eps_actual": 0.15, "eps_estimate": 0.18, "eps_surprise_pct": -14.23, "revenue": null, "revenue_yoy": null}, {"date": "2023-11-07", "time": "06:00", "eps_actual": 0.3, "eps_estimate": 0.16, "eps_surprise_pct": 91.85, "revenue": null, "revenue_yoy": null}, {"date": "2023-08-08", "time": "16:00", "eps_actual": 0.2, "eps_estimate": 0.09, "eps_surprise_pct": 124.22, "revenue": null, "revenue_yoy": null}]}