{"ticker": "CUZ", "quarters": [{"date": "2026-04-30", "time": "16:00", "eps_actual": null, "eps_estimate": 0.06, "eps_surprise_pct": null, "revenue": null, "revenue_yoy": null}, {"date": "2026-02-05", "time": "16:00", "eps_actual": 0.06, "eps_estimate": 0.06, "eps_surprise_pct": 8.0, "revenue": 255034000, "revenue_yoy": 13.2}, {"date": "2025-10-30", "time": "16:00", "eps_actual": 0.05, "eps_estimate": 0.1, "eps_surprise_pct": -48.83, "revenue": 248326000, "revenue_yoy": null}, {"date": "2025-07-31", "time": "16:00", "eps_actual": 0.09, "eps_estimate": 0.08, "eps_surprise_pct": 12.5, "revenue": 240128000, "revenue_yoy": null}, {"date": "2025-05-01", "time": "16:00", "eps_actual": 0.12, "eps_estimate": 0.07, "eps_surprise_pct": 71.43, "revenue": 250328000, "revenue_yoy": null}, {"date": "2025-02-06", "time": "16:00", "eps_actual": 0.09, "eps_estimate": 0.11, "eps_surprise_pct": -18.18, "revenue": 225327000, "revenue_yoy": null}, {"date": "2024-10-24", "time": "16:00", "eps_actual": 0.07, "eps_estimate": 0.07, "eps_surprise_pct": null, "revenue": null, "revenue_yoy": null}, {"date": "2024-07-25", "time": "16:00", "eps_actual": 0.05, "eps_estimate": 0.09, "eps_surprise_pct": -44.44, "revenue": null, "revenue_yoy": null}, {"date": "2024-04-25", "time": "16:00", "eps_actual": 0.09, "eps_estimate": 0.12, "eps_surprise_pct": -27.92, "revenue": null, "revenue_yoy": null}, {"date": "2024-02-07", "time": "16:00", "eps_actual": 0.12, "eps_estimate": 0.12, "eps_surprise_pct": 2.92, "revenue": null, "revenue_yoy": null}, {"date": "2023-10-26", "time": "16:00", "eps_actual": 0.13, "eps_estimate": 0.12, "eps_surprise_pct": 5.06, "revenue": null, "revenue_yoy": null}, {"date": "2023-07-27", "time": "16:00", "eps_actual": 0.15, "eps_estimate": 0.16, "eps_surprise_pct": -4.59, "revenue": null, "revenue_yoy": null}]}