{"ticker": "KBR", "quarters": [{"date": "2026-05-06", "time": "08:00", "eps_actual": null, "eps_estimate": 0.95, "eps_surprise_pct": null, "revenue": null, "revenue_yoy": null}, {"date": "2026-02-26", "time": "06:00", "eps_actual": 0.99, "eps_estimate": 0.95, "eps_surprise_pct": 4.39, "revenue": 1885000000, "revenue_yoy": -11.2}, {"date": "2025-10-30", "time": "06:00", "eps_actual": 1.02, "eps_estimate": 0.95, "eps_surprise_pct": 6.87, "revenue": 1931000000, "revenue_yoy": null}, {"date": "2025-07-31", "time": "06:00", "eps_actual": 0.91, "eps_estimate": 0.88, "eps_surprise_pct": 2.99, "revenue": 1952000000, "revenue_yoy": null}, {"date": "2025-05-06", "time": "06:00", "eps_actual": 0.98, "eps_estimate": 0.86, "eps_surprise_pct": 13.71, "revenue": 2055000000, "revenue_yoy": null}, {"date": "2025-02-24", "time": "16:00", "eps_actual": 0.91, "eps_estimate": 0.82, "eps_surprise_pct": 11.38, "revenue": 2122000000, "revenue_yoy": null}, {"date": "2024-10-23", "time": "06:00", "eps_actual": 0.84, "eps_estimate": 0.84, "eps_surprise_pct": 0.17, "revenue": null, "revenue_yoy": null}, {"date": "2024-07-24", "time": "06:00", "eps_actual": 0.83, "eps_estimate": 0.79, "eps_surprise_pct": 4.72, "revenue": null, "revenue_yoy": null}, {"date": "2024-04-30", "time": "06:00", "eps_actual": 0.77, "eps_estimate": 0.7, "eps_surprise_pct": 9.93, "revenue": null, "revenue_yoy": null}, {"date": "2024-02-20", "time": "06:00", "eps_actual": 0.69, "eps_estimate": 0.69, "eps_surprise_pct": 0.51, "revenue": null, "revenue_yoy": null}, {"date": "2023-11-02", "time": "06:00", "eps_actual": 0.75, "eps_estimate": 0.74, "eps_surprise_pct": 0.86, "revenue": null, "revenue_yoy": null}, {"date": "2023-07-27", "time": "06:00", "eps_actual": 0.74, "eps_estimate": 0.72, "eps_surprise_pct": 3.05, "revenue": null, "revenue_yoy": null}]}