{"ticker": "LOW", "quarters": [{"date": "2026-05-20", "time": "08:00", "eps_actual": null, "eps_estimate": 2.88, "eps_surprise_pct": null, "revenue": null, "revenue_yoy": null}, {"date": "2026-02-25", "time": "06:00", "eps_actual": 1.98, "eps_estimate": 1.94, "eps_surprise_pct": 1.93, "revenue": null, "revenue_yoy": null}, {"date": "2025-11-19", "time": "06:00", "eps_actual": 3.06, "eps_estimate": 2.95, "eps_surprise_pct": 3.61, "revenue": 20813000000, "revenue_yoy": 3.2}, {"date": "2025-08-20", "time": "06:00", "eps_actual": 4.33, "eps_estimate": 4.24, "eps_surprise_pct": 2.18, "revenue": 23959000000, "revenue_yoy": null}, {"date": "2025-05-21", "time": "06:00", "eps_actual": 2.92, "eps_estimate": 2.88, "eps_surprise_pct": 1.4, "revenue": 20930000000, "revenue_yoy": null}, {"date": "2025-02-26", "time": "06:00", "eps_actual": 1.93, "eps_estimate": 1.84, "eps_surprise_pct": 4.84, "revenue": 18554000000, "revenue_yoy": null}, {"date": "2024-11-19", "time": "06:00", "eps_actual": 2.89, "eps_estimate": 2.81, "eps_surprise_pct": 2.77, "revenue": 20170000000, "revenue_yoy": null}, {"date": "2024-08-20", "time": "06:00", "eps_actual": 4.1, "eps_estimate": 4.0, "eps_surprise_pct": 2.58, "revenue": null, "revenue_yoy": null}, {"date": "2024-05-21", "time": "06:00", "eps_actual": 3.06, "eps_estimate": 2.95, "eps_surprise_pct": 3.64, "revenue": null, "revenue_yoy": null}, {"date": "2024-02-27", "time": "06:00", "eps_actual": 1.77, "eps_estimate": 1.68, "eps_surprise_pct": 5.25, "revenue": null, "revenue_yoy": null}, {"date": "2023-11-21", "time": "06:00", "eps_actual": 3.06, "eps_estimate": 3.03, "eps_surprise_pct": 0.94, "revenue": null, "revenue_yoy": null}, {"date": "2023-08-22", "time": "06:00", "eps_actual": 4.56, "eps_estimate": 4.48, "eps_surprise_pct": 1.79, "revenue": null, "revenue_yoy": null}]}