{"ticker": "MHK", "quarters": [{"date": "2026-04-30", "time": "16:00", "eps_actual": null, "eps_estimate": 1.82, "eps_surprise_pct": null, "revenue": null, "revenue_yoy": null}, {"date": "2026-02-12", "time": "16:00", "eps_actual": 2.0, "eps_estimate": 1.98, "eps_surprise_pct": 1.12, "revenue": 2699700000, "revenue_yoy": 2.4}, {"date": "2025-10-23", "time": "16:00", "eps_actual": 2.67, "eps_estimate": 2.64, "eps_surprise_pct": 1.16, "revenue": 2757900000, "revenue_yoy": null}, {"date": "2025-07-24", "time": "16:00", "eps_actual": 2.77, "eps_estimate": 2.61, "eps_surprise_pct": 6.3, "revenue": 2802100000, "revenue_yoy": null}, {"date": "2025-05-01", "time": "16:00", "eps_actual": 1.52, "eps_estimate": 1.41, "eps_surprise_pct": 8.18, "revenue": 2525800000, "revenue_yoy": null}, {"date": "2025-02-06", "time": "16:00", "eps_actual": 1.95, "eps_estimate": 1.85, "eps_surprise_pct": 5.35, "revenue": 2637200000, "revenue_yoy": null}, {"date": "2024-10-24", "time": "16:00", "eps_actual": 2.9, "eps_estimate": 2.89, "eps_surprise_pct": 0.48, "revenue": null, "revenue_yoy": null}, {"date": "2024-07-25", "time": "16:00", "eps_actual": 3.0, "eps_estimate": 2.75, "eps_surprise_pct": 9.06, "revenue": null, "revenue_yoy": null}, {"date": "2024-04-25", "time": "16:00", "eps_actual": 1.86, "eps_estimate": 1.68, "eps_surprise_pct": 10.96, "revenue": null, "revenue_yoy": null}, {"date": "2024-02-08", "time": "16:00", "eps_actual": 1.96, "eps_estimate": 1.86, "eps_surprise_pct": 5.43, "revenue": null, "revenue_yoy": null}, {"date": "2023-10-26", "time": "16:00", "eps_actual": 2.72, "eps_estimate": 2.65, "eps_surprise_pct": 2.63, "revenue": null, "revenue_yoy": null}, {"date": "2023-07-27", "time": "16:00", "eps_actual": 2.76, "eps_estimate": 2.65, "eps_surprise_pct": 4.09, "revenue": null, "revenue_yoy": null}]}